demo/__init__.py
demo/run.py
demo/pages/__init__.py
demo/pages/ios_page.py
demo/pages/ocr_page.py
demo/tests/__init__.py
demo/tests/test_ios.py
demo/tests/test_ocr.py
testios/__init__.py
testios/case.py
testios/cli.py
testios/page.py
testios/scaffold.py
testios/core/__init__.py
testios/core/api/__init__.py
testios/core/api/request.py
testios/core/image/__init__.py
testios/core/image/driver.py
testios/core/image/element.py
testios/core/ios/__init__.py
testios/core/ios/common.py
testios/core/ios/driver.py
testios/core/ios/element.py
testios/core/ocr/__init__.py
testios/core/ocr/driver.py
testios/core/ocr/element.py
testios/running/__init__.py
testios/running/conf.yml
testios/running/runner.py
testios/testdata/__init__.py
testios/testdata/data.py
testios/utils/__init__.py
testios/utils/allure_util.py
testios/utils/common.py
testios/utils/config.py
testios/utils/des_util.py
testios/utils/dingtalk.py
testios/utils/excel.py
testios/utils/exceptions.py
testios/utils/log.py
testios/utils/mail.py
testios/utils/mysql_util.py
testios/utils/pytest_util.py
testios/utils/swagger_util.py
testios-0.0.7.dist-info/METADATA
testios-0.0.7.dist-info/WHEEL
testios-0.0.7.dist-info/entry_points.txt
testios-0.0.7.dist-info/top_level.txt
testios-0.0.7.dist-info/RECORD
