Metadata-Version: 2.1
Name: testios
Version: 0.0.7
Summary: IOS平台自动化测试框架
Home-page: https://gitee.com/bluepang2021/testios
Author: 杨康
Author-email: 772840356@qq.com
Platform: IOS
Classifier: Programming Language :: Python :: 3.9
Requires-Python: >=3.9
Requires-Dist: requests-toolbelt (==0.10.1)
Requires-Dist: jmespath (==0.9.5)
Requires-Dist: jsonschema (==4.17.0)
Requires-Dist: pytest (==6.2.5)
Requires-Dist: pytest-rerunfailures (==10.2)
Requires-Dist: pytest-xdist (==2.5.0)
Requires-Dist: allure-pytest (==2.9.45)
Requires-Dist: click (~=8.1.3)
Requires-Dist: loguru (==0.7.0)
Requires-Dist: urllib3 (==1.26.15)
Requires-Dist: PyYAML (~=6.0)
Requires-Dist: tidevice (==0.6.1)
Requires-Dist: facebook-wda (==1.4.6)
Requires-Dist: opencv-python (==4.6.0.66)
Requires-Dist: filelock (==3.12.2)
